ingest_anything/__init__.py
ingest_anything/add_types.py
ingest_anything/agent.py
ingest_anything/agent_types.py
ingest_anything/crawlee_utils.py
ingest_anything/embeddings.py
ingest_anything/ingestion.py
ingest_anything/web_ingestion.py
ingest_anything-1.3.1.dist-info/METADATA
ingest_anything-1.3.1.dist-info/WHEEL
ingest_anything-1.3.1.dist-info/licenses/LICENSE
ingest_anything-1.3.1.dist-info/RECORD
