Metadata-Version: 2.4
Name: ingest-anything
Version: 1.3.1
Summary: ingest-anything: from data to vector database effortlessly
Project-URL: Homepage, https://github.com/AstraBert/ingest-anything
Project-URL: Issues, https://github.com/AstraBert/ingest-anything/issues
Author-email: "Clelia (Astra) Bertelli" <astraberte9@gmail.com>
License-File: LICENSE
Classifier: License :: OSI Approved :: MIT License
Classifier: Operating System :: OS Independent
Classifier: Programming Language :: Python :: 3
Requires-Python: <3.13,>=3.10
Requires-Dist: chonkie[all]
Requires-Dist: crawlee[beautifulsoup]
Requires-Dist: llama-index-readers-file
Requires-Dist: pdfitdown
Requires-Dist: pydantic
